{
    "name": "ball_hit_ground_10",
    "objects": {
        "green_ball": {
            "type": "ball",
            "radius": 0.2891883316733973,
            "x": -0.22264542062103598,
            "y": 4.9,
            "color": "green",
            "dynamic": true
        },
        "red_ball": {
            "type": "ball",
            "radius": 0.5,
            "x": -1.9715894128135734,
            "y": 1.2561764989494906,
            "color": "red",
            "dynamic": true
        },
        "purple_platform": {
            "type": "platform",
            "length": 10,
            "angle": 0,
            "x": 0,
            "y": -4.9,
            "color": "purple",
            "dynamic": false
        },
        "high_platform": {
            "type": "platform",
            "length": 1.743106263727894,
            "angle": 0,
            "x": -0.44529084124207197,
            "y": -1.3719058093566245,
            "color": "black",
            "dynamic": false
        }
    },
    "target_object": "green_ball",
    "goal_object": "purple_platform",
    "action_objects": [
        "red_ball"
    ],
    "solution": [
        -0.9711356163024902,
        0.26444968581199646
    ]
}